jtool-0.2.0.data/scripts/jtool
jtool-0.2.0.dist-info/METADATA
jtool-0.2.0.dist-info/WHEEL
jtool/__init__.py
jtool/__main__.py
jtool-0.2.0.dist-info/RECORD
