Metadata-Version: 2.4
Name: jtool
Version: 0.2.0
Classifier: Development Status :: 4 - Beta
Classifier: Intended Audience :: Developers
Classifier: License :: OSI Approved :: MIT License
Classifier: License :: OSI Approved :: Apache Software License
Classifier: Programming Language :: Rust
Classifier: Programming Language :: Python :: 3
Classifier: Programming Language :: Python :: 3.8
Classifier: Programming Language :: Python :: 3.9
Classifier: Programming Language :: Python :: 3.10
Classifier: Programming Language :: Python :: 3.11
Classifier: Programming Language :: Python :: 3.12
Classifier: Topic :: Software Development :: Libraries :: Python Modules
Summary: Fast Jupyter notebook management tool (Rust rewrite)
Keywords: jupyter,notebook,cli,rust
Home-Page: https://github.com/paradigmxyz/jtool
Author: jtool contributors
License: MIT OR Apache-2.0
Requires-Python: >=3.8
Project-URL: Repository, https://github.com/paradigmxyz/jtool
Project-URL: Documentation, https://github.com/paradigmxyz/jtool
